<?xml version="1.0" encoding="utf-8"?>
<!-- Русский перевод групп совместимости 1-2-3 Personalities. Вычитан и пересобран 2026-07-10 под
     регистр ядра (DiaryInteractionGroupDefs): «поселенец», а не «пешка»; ярлыки с заглавной;
     нумерованные инструкции в стиле «тема: пиши…». Индексы instructions.N / tones.N соответствуют
     порядку <li> в 1.6/Defs/DiaryCompat_123Personalities.xml — НЕ менять порядок и НЕ удалять строки
     (иначе индексы разъедутся). .label виден в настройках, .instruction/.tone уходят в подсказку модели. -->
<LanguageData>

  <personalities123_thoughts.label>Настроения по характеру</personalities123_thoughts.label>
  <personalities123_thoughts.instruction>настроение под стать складу поселенца; пиши само чувство и дай нраву проступить в том, как поселенец его принимает, — а тип характера не называй</personalities123_thoughts.instruction>
  <personalities123_thoughts.instructions.0>настроение по характеру: пиши чувство так, как принял бы его человек этого склада</personalities123_thoughts.instructions.0>
  <personalities123_thoughts.instructions.1>настроение по характеру: держись одного честного чувства; это настроение, подкрашенное нравом, а не событие</personalities123_thoughts.instructions.1>
  <personalities123_thoughts.tone>с оттенком собственного нрава поселенца</personalities123_thoughts.tone>
  <personalities123_thoughts.tones.0>не изменяя нраву поселенца, то же событие прожито на его лад</personalities123_thoughts.tones.0>
  <personalities123_thoughts.tones.1>тихо и про себя, настроение пропущено сквозь собственный склад</personalities123_thoughts.tones.1>

  <personalities123_interactions.label>Совместимость характеров</personalities123_interactions.label>
  <personalities123_interactions.instruction>встретились два нрава; пиши совпадение или трение, которое эти двое почувствовали, а не то, какими словами обменялись</personalities123_interactions.instruction>
  <personalities123_interactions.instructions.0>совместимость характеров: напиши, легче ли поселенцу рядом с этим человеком или тот его раздражает — и откуда это взялось</personalities123_interactions.instructions.0>
  <personalities123_interactions.instructions.1>совместимость характеров: назови сходство или различие, которое за этим стоит, но только как его чувствует сам поселенец — без ярлыков</personalities123_interactions.instructions.1>
  <personalities123_interactions.instructions.2>совместимость характеров: пиши только про эту встречу, не вынося приговора всем их отношениям</personalities123_interactions.instructions.2>
  <personalities123_interactions.tone>с чутьём к тому, как эти двое ладят</personalities123_interactions.tone>
  <personalities123_interactions.tones.0>наблюдательно, по мелочам угадывая чужой нрав — где ладится, а где скребёт</personalities123_interactions.tones.0>
  <personalities123_interactions.tones.1>тихо и лично, с каким чувством поселенец уходит именно от этого человека</personalities123_interactions.tones.1>

</LanguageData>
